[
  {
    "id": "11111111-1111-4111-8111-111111111101",
    "name": "Country flags",
    "slug": "country-flags",
    "description": null,
    "kind": "country_flags",
    "isApproved": true,
    "parentId": null,
    "displayOrder": 10,
    "createdAt": "2026-01-15T12:00:00.000Z",
    "updatedAt": "2026-01-15T12:00:00.000Z"
  },
  {
    "id": "11111111-1111-4111-8111-111111111105",
    "name": "Autonomous & regional flags",
    "slug": "autonomous-flags",
    "description": null,
    "kind": "autonomy_flags",
    "isApproved": true,
    "parentId": null,
    "displayOrder": 15,
    "createdAt": "2026-01-15T12:00:00.000Z",
    "updatedAt": "2026-01-15T12:00:00.000Z"
  },
  {
    "id": "11111111-1111-4111-8111-111111111102",
    "name": "Historical flags",
    "slug": "historical-flags",
    "description": null,
    "kind": "historical_flags",
    "isApproved": true,
    "parentId": null,
    "displayOrder": 20,
    "createdAt": "2026-01-15T12:00:00.000Z",
    "updatedAt": "2026-01-15T12:00:00.000Z"
  },
  {
    "id": "11111111-1111-4111-8111-111111111103",
    "name": "International organization flags",
    "slug": "organization-flags",
    "description": null,
    "kind": "organization_flags",
    "isApproved": true,
    "parentId": null,
    "displayOrder": 25,
    "createdAt": "2026-01-15T12:00:00.000Z",
    "updatedAt": "2026-01-15T12:00:00.000Z"
  },
  {
    "id": "11111111-1111-4111-8111-111111111106",
    "name": "Institution & federation flags",
    "slug": "institution-flags",
    "description": null,
    "kind": "institution_flags",
    "isApproved": true,
    "parentId": null,
    "displayOrder": 30,
    "createdAt": "2026-01-15T12:00:00.000Z",
    "updatedAt": "2026-01-15T12:00:00.000Z"
  },
  {
    "id": "11111111-1111-4111-8111-111111111107",
    "name": "Flag mockups",
    "slug": "flag-mockups",
    "description": null,
    "kind": "flag_mockups",
    "isApproved": true,
    "parentId": null,
    "displayOrder": 35,
    "createdAt": "2026-01-15T12:00:00.000Z",
    "updatedAt": "2026-01-15T12:00:00.000Z"
  },
  {
    "id": "11111111-1111-4111-8111-111111111108",
    "name": "Flag videos",
    "slug": "flag-videos",
    "description": null,
    "kind": "flag_videos",
    "isApproved": true,
    "parentId": null,
    "displayOrder": 40,
    "createdAt": "2026-01-15T12:00:00.000Z",
    "updatedAt": "2026-01-15T12:00:00.000Z"
  },
  {
    "id": "11111111-1111-4111-8111-111111111109",
    "name": "Flag icons",
    "slug": "flag-icons",
    "description": null,
    "kind": "flag_icons",
    "isApproved": true,
    "parentId": null,
    "displayOrder": 45,
    "createdAt": "2026-01-15T12:00:00.000Z",
    "updatedAt": "2026-01-15T12:00:00.000Z"
  },
  {
    "id": "11111111-1111-4111-8111-111111111104",
    "name": "Approved misc",
    "slug": "other-approved",
    "description": null,
    "kind": "other",
    "isApproved": true,
    "parentId": null,
    "displayOrder": 90,
    "createdAt": "2026-01-15T12:00:00.000Z",
    "updatedAt": "2026-01-15T12:00:00.000Z"
  },
  {
    "id": "11111111-1111-4111-8111-111111111110",
    "name": "Country coats of arms",
    "slug": "country-coats",
    "description": "Official national coats of arms and state emblems from countries around the world.",
    "kind": "country_coats",
    "isApproved": true,
    "parentId": null,
    "displayOrder": 91,
    "createdAt": "2026-06-14T12:00:00.000Z",
    "updatedAt": "2026-06-14T12:00:00.000Z"
  },
  {
    "id": "11111111-1111-4111-8111-111111111111",
    "name": "Historical coats of arms",
    "slug": "historical-coats",
    "description": "Coats of arms and heraldic emblems from historical states, dynasties and empires.",
    "kind": "historical_coats",
    "isApproved": true,
    "parentId": null,
    "displayOrder": 92,
    "createdAt": "2026-06-14T12:00:00.000Z",
    "updatedAt": "2026-06-14T12:00:00.000Z"
  },
  {
    "id": "11111111-1111-4111-8111-111111111112",
    "name": "Football club logos",
    "slug": "football-clubs",
    "description": "Crests and logos of professional football clubs from leagues around the world.",
    "kind": "football_clubs",
    "isApproved": true,
    "parentId": null,
    "displayOrder": 93,
    "createdAt": "2026-06-14T12:00:00.000Z",
    "updatedAt": "2026-06-14T12:00:00.000Z"
  }
]
